evalmath.py
evalmath-1.0.0.dist-info/LICENSE.txt
evalmath-1.0.0.dist-info/METADATA
evalmath-1.0.0.dist-info/WHEEL
evalmath-1.0.0.dist-info/top_level.txt
evalmath-1.0.0.dist-info/RECORD
